README.md
setup.py
touchtext/__init__.py
touchtext/functional.py
touchtext/wget.py
touchtext.egg-info/PKG-INFO
touchtext.egg-info/SOURCES.txt
touchtext.egg-info/dependency_links.txt
touchtext.egg-info/requires.txt
touchtext.egg-info/top_level.txt
touchtext/_internal/__init__.py
touchtext/_internal/module_utils.py
touchtext/data/__init__.py
touchtext/data/datasets_utils.py
touchtext/data/functional.py
touchtext/data/metrics.py
touchtext/data/utils.py
touchtext/datasets/__init__.py
touchtext/datasets/multi30k.py
touchtext/vocab/__init__.py
touchtext/vocab/vectors.py
touchtext/vocab/vocab.py
touchtext/vocab/vocab_factory.py